rotationset.py
rotationset-0.1.0.dist-info/LICENSE
rotationset-0.1.0.dist-info/METADATA
rotationset-0.1.0.dist-info/WHEEL
rotationset-0.1.0.dist-info/RECORD
