Metadata-Version: 2.1
Name: rotationset
Version: 0.1.0
Summary: Extension of the scipy Rotation class to sets of rotations.
License: MIT
Author: Gereon Tombrink
Author-email: tombrink@igg.uni-bonn.de
Requires-Python: >=3.8.2,<3.12
Classifier: License :: OSI Approved :: MIT License
Classifier: Programming Language :: Python :: 3
Classifier: Programming Language :: Python :: 3.9
Classifier: Programming Language :: Python :: 3.10
Classifier: Programming Language :: Python :: 3.11
Requires-Dist: numpy (>=1.24.4)
Requires-Dist: scipy (>=1.10.1)
